setup.py
user_utils/__init__.py
user_utils/mongodbio.py
user_utils/user_transforms.py
users_pipeline.egg-info/PKG-INFO
users_pipeline.egg-info/SOURCES.txt
users_pipeline.egg-info/dependency_links.txt
users_pipeline.egg-info/top_level.txt