Metadata-Version: 2.1
Name: users-pipeline
Version: 0.1
Summary: Users Pipeline Workflow Package.
Home-page: https://bitbucket.org/fleetopsteam/fleetops-gcp-pipeline
Author: Kaya Smith
Author-email: kaya@fleetops.ai
License: UNKNOWN
Platform: UNKNOWN
Classifier: Programming Language :: Python :: 2
Classifier: License :: OSI Approved :: MIT License
Classifier: Operating System :: OS Independent
